skippex/__init__.py
skippex/__main__.py
skippex/auth.py
skippex/cmd.py
skippex/core.py
skippex/notifications.py
skippex/seekables.py
skippex/sessions.py
skippex/stores.py
skippex-0.2.4.dist-info/entry_points.txt
skippex-0.2.4.dist-info/LICENSE
skippex-0.2.4.dist-info/WHEEL
skippex-0.2.4.dist-info/METADATA
skippex-0.2.4.dist-info/RECORD
