Metadata-Version: 2.1
Name: skippex
Version: 0.2.4
Summary: Automatic 'skip intro' for Plex with Chromecast support
Home-page: https://github.com/sprt/skippex
License: MPL-2.0
Keywords: plex,chromecast,mediaserver
Author: sprt
Author-email: hellosprt@gmail.com
Requires-Python: >=3.6,<4.0
Classifier: Development Status :: 4 - Beta
Classifier: Environment :: Console
Classifier: Intended Audience :: End Users/Desktop
Classifier: License :: OSI Approved
Classifier: Programming Language :: Python :: 3
Classifier: Programming Language :: Python :: 3.6
Classifier: Programming Language :: Python :: 3.7
Classifier: Programming Language :: Python :: 3.8
Classifier: Programming Language :: Python :: 3.9
Classifier: Topic :: Multimedia :: Video
Requires-Dist: PlexAPI (>=4.2.0,<5.0.0)
Requires-Dist: PyChromecast (>=7.7.1,<8.0.0)
Requires-Dist: dataclasses (>=0.7,<0.8); python_version < "3.7"
Requires-Dist: pid (>=3.0.4,<4.0.0)
Requires-Dist: requests (>=2.25.1,<3.0.0)
Requires-Dist: typing-extensions (>=3.7.4,<4.0.0)
Requires-Dist: websocket_client (>=0.57.0,<0.58.0)
Requires-Dist: wrapt (>=1.12.1,<2.0.0)
Requires-Dist: xdg (>=5.0.1,<6.0.0)
Requires-Dist: zeroconf (>=0.28.8,<0.29.0)
Project-URL: Repository, https://github.com/sprt/skippex
